local_qwen3b_part006/__init__.py
local_qwen3b_part006/qwen2.5-3b-instruct-q5_k_m.gguf.part_006
local_qwen3b_part006-0.0.1.dist-info/METADATA
local_qwen3b_part006-0.0.1.dist-info/WHEEL
local_qwen3b_part006-0.0.1.dist-info/top_level.txt
local_qwen3b_part006-0.0.1.dist-info/RECORD
